<?xml version="1.0" encoding="UTF-8"?>
<LanguageData>

  <EditorLabel>World editor</EditorLabel>
  <WorldTemplates>Loaded templates</WorldTemplates>
  <isEnableEditorLabel>Enable</isEnableEditorLabel>
  
  <DeleteSingleRoad>Delete the selected road</DeleteSingleRoad>
  <DeleteRangeRoads>Delete range of roads</DeleteRangeRoads>
  <DeleteSingleRiver>Delete the selected river</DeleteSingleRiver>
  <DeleteRangeRivers>Delete range of rivers</DeleteRangeRivers>
  <DeleteAllRoads>Удалить все дороги</DeleteAllRoads>
  <DeleteAllRivers>Удалить все реки</DeleteAllRivers>
  
  <SaveWorldTemplate>Save world template</SaveWorldTemplate>
  <SelectedStorytellerTitle>Storyteller</SelectedStorytellerTitle>
    
  <StartTileLabel>Start</StartTileLabel>
  <EndTileLabel>End</EndTileLabel>
  <CreateRoadLabel>Create road(s)</CreateRoadLabel>
  <CreateRiverLael>Create river(s)</CreateRiverLael>
  
  <ClearAllHillnses>Delete All Mountains</ClearAllHillnses>
  <SetTileToAllMap>Set biome to all tiles</SetTileToAllMap>
  
  <SetHillnesToAllMap>Установить горы на всю карту</SetHillnesToAllMap>
  <SetHillnesToAllBiome>Установить горы на тайлы выбранного биома</SetHillnesToAllBiome>
  <SetToAllMap>Установить на всю карту</SetToAllMap>
  <SetToAllBiome>Установить на выбранный биом</SetToAllBiome>
  
  <UpdateAllTiles>Update all tiles</UpdateAllTiles>
  <UpdateAllTilesInfo>Updates information about all tiles</UpdateAllTilesInfo>
  <UpdateCustomLayer>Update layer</UpdateCustomLayer>
  <UpdateCustomLayerInfo>Updates the selected layer</UpdateCustomLayerInfo>
  <UpdateImmediatelyON>Immediate update [ON]</UpdateImmediatelyON>
  <UpdateImmediatelyOFF>Immediate update [OFF]</UpdateImmediatelyOFF>
  <UpdateImmediatelyInfo>Enables immediate tile update</UpdateImmediatelyInfo>
  
  <Biome>Biome</Biome>
  <NoText>No</NoText>
  <Temperature>Temperature</Temperature>
  <Evelation>Evelation</Evelation>
  <Rainfall>Rainfall</Rainfall>
  <Swampiness>Swampiness</Swampiness>
	
  <FactionEditor>Faction editor</FactionEditor>
  <RoadAndRiverEditor>Roads and rivers editor</RoadAndRiverEditor>
  
  <SetFraction>Set faction</SetFraction>
  <AllFactionsList>All avaliable factions</AllFactionsList>
  <AllSpawnedFactionsList>All spawn faction</AllSpawnedFactionsList>
  <CustomFactionName>Faction name:</CustomFactionName>
  <CustomFactionLore>Description:</CustomFactionLore>
  <isVisitable>Visitable:</isVisitable>
  <UseCustomColor>Color</UseCustomColor>
  <RedLabel>Red</RedLabel>
  <GreenLabel>Green</GreenLabel>
  <BlueLabel>Blue</BlueLabel>
  
  <FactionManager>Faction management</FactionManager>
  <SettlementManager>Settlement management</SettlementManager>
  
  <FactionManagerTitle>Factions on the map</FactionManagerTitle>
  <RemoveSpawnedFaction>Delete faction</RemoveSpawnedFaction>
  <DeleteAllSettlements>Delete all settlements</DeleteAllSettlements>
  <AddNewFaction>Create new faction</AddNewFaction>
  <EditSelectedFaction>Edit faction</EditSelectedFaction>
  
  <FactionCreatorTitle>Create new faction</FactionCreatorTitle>
  <RandomizeFaction>Generate</RandomizeFaction>
  <RandomizeName>Random name</RandomizeName>
  <ClearFaction>Clear</ClearFaction>
  <FactionDefName>Parent:</FactionDefName>
  <FactionName>Name</FactionName>
  <FactionDefeated>Defeated?</FactionDefeated>
  <isDefeatedYES>Yes</isDefeatedYES>
  <isDefeatedNO>No</isDefeatedNO>
  <FactionRelative>Relations</FactionRelative>
  <FactionInfoName>Faction:</FactionInfoName>
  <FactionGoodness>Relation</FactionGoodness>
  <FactionMelanin>???</FactionMelanin>
  <ColorSpectrum>Color</ColorSpectrum>
  <AddNewRelative>Add</AddNewRelative>
  <DeleteRelative>Delete</DeleteRelative>
  <GenerateRelative>Generate</GenerateRelative>
  <FactionLeaderName>Leader</FactionLeaderName>
  <CreateNewFaction>Create faction</CreateNewFaction>
  
  <FactionEditTitle>Edit faction</FactionEditTitle>
  <SaveFaction>Save</SaveFaction>
  
  <AddNewSettlement>Create new settlement</AddNewSettlement>
  <SettlementManagerTitle>Settlement on the map</SettlementManagerTitle>
  <RemoveSpawnedSettlement>Delete settlement</RemoveSpawnedSettlement>
  <EditSelectedSettlement>Editor settlement</EditSelectedSettlement>
  <RemoveAllSpawnedSettlement>Delete all settlement</RemoveAllSpawnedSettlement>
  <RemoveAllFeatures>Delete all features</RemoveAllFeatures>
  
  <SettlementCreatorTitle>Create new settlement</SettlementCreatorTitle>
  <SettlementNameField>Name</SettlementNameField>
  <CreateNewSettlement>Create new settlement</CreateNewSettlement>
  
  <SettlementEditTitle>Edit settlement</SettlementEditTitle>
  <SettlementNameField>Name</SettlementNameField>
  <SaveNewSettlement>Save</SaveNewSettlement>
  
  <AddRelativeTitle>Add relative</AddRelativeTitle>
  <Cancel>Cancel</Cancel>
  
  <FixRelatives>Fix relation of the selected faction</FixRelatives>
  
  <SettlementMarketTitle>Goods</SettlementMarketTitle>
  <EditMarketList>Goods</EditMarketList>
  <CountMarket>Count:</CountMarket>
  <MarketValue>Market value:</MarketValue>
  <DeleteGood>Delete</DeleteGood>
  <RegenerateStock>Generate new goods</RegenerateStock>
  <AddNewItemIntoStock>Add custom item</AddNewItemIntoStock>
  
  <ItemListTitle>Custom items</ItemListTitle>
  <Category>Category</Category>
  <GenerateItem>Generate and add</GenerateItem>
  <Quality>Quality</Quality>
  <StackCount>Stack count</StackCount>
  
  <WorldFeaturesEditor>World Objects</WorldFeaturesEditor>
  <WorldPrintsTitle>World Features</WorldPrintsTitle>
  <DeleteFeature>Delete feature</DeleteFeature>
  <WorldFeatureName>Name</WorldFeatureName>
  <CreateNewFeature>Create</CreateNewFeature>
  <RotateFeature>Angle</RotateFeature>
  <FeatureLengthMax>Size</FeatureLengthMax>
  <CreateNewWorldPrint>Create new feature</CreateNewWorldPrint>
  
  <SelectScenario>Scenario</SelectScenario>
  <SelectStorytellerTitle>Storyteller</SelectStorytellerTitle>
  <CreateTemplate>Create template</CreateTemplate>
  
  <CreateNewObject>Add world object</CreateNewObject>
  <DeleteObject>Delete selected object</DeleteObject>
  <RemoveAllObjects>Delete all objects</RemoveAllObjects>
  
   <ThreatPoint>Threat points (empty for auto)</ThreatPoint>
  
</LanguageData>